command_upd/__init__.py
command_upd-0.1.1.dist-info/METADATA
command_upd-0.1.1.dist-info/WHEEL
command_upd-0.1.1.dist-info/entry_points.txt
command_upd-0.1.1.dist-info/RECORD
